pubmed_fetcher/__init__.py
pubmed_fetcher/export.py
pubmed_fetcher/fetch.py
pubmed_fetcher/filter.py
shafak07_pubmed_fetcher-0.1.0.dist-info/entry_points.txt
shafak07_pubmed_fetcher-0.1.0.dist-info/METADATA
shafak07_pubmed_fetcher-0.1.0.dist-info/WHEEL
shafak07_pubmed_fetcher-0.1.0.dist-info/RECORD
